{
	"Generic   USB  Joystick": {
		"Y": "Button1",
		"B": "Button2",
		"A": "Button3",
		"X": "Button4",
		"LTrigger": "Button5",
		"RTrigger": "Button6",
		"LBumper": "Button7",
		"RBumper": "Button8",
		"LStickBtn": "Button9",
		"RStickBtn": "Button10",
		"Select": "Button11",
		"Start": "Button12",
		"dPadUp": "dPad0_0",
		"dPadDown": "dPad0_180",
		"dPadLeft": "dPad0_270",
		"dPadRight": "dPad0_90",
		"LStickLeft": "Stick0_-1",
		"LStickRight": "Stick0_1",
		"LStickUp": "Stick1_-1",
		"LStickDown": "Stick1_1",
		"RStickLeft": "Stick2_-1",
		"RStickRight": "Stick2_1",
		"RStickUp": "Stick4_-1",
		"RStickDown": "Stick4_1"
	},
	"Controller (Gamepad F310)": {
		"A": "Button1",
		"B": "Button2",
		"X": "Button3",
		"Y": "Button4",
		"LTrigger": "Button5",
		"RTrigger": "Button6",
		"Back": "Button7",
		"Start": "Button8",
		"LStickBtn": "Button9",
		"RStickBtn": "Button10",
		"dPadUp": "dPad0_0",
		"dPadDown": "dPad0_180",
		"dPadLeft": "dPad0_270",
		"dPadRight": "dPad0_90"
	}
}